seco/__init__.py
seco/range/__init__.py
seco/range/sync/__init__.py
seco/range/sync/constants.py
seco/range/sync/git_sync.py
seco/range/sync/http.py
seco/range/sync/index.py
seco/range/sync/local.py
seco/range/sync/svn.py
seco/range/sync/version.py
python3_seco_range-1.0.2.dist-info/LICENSE.txt
python3_seco_range-1.0.2.dist-info/METADATA
python3_seco_range-1.0.2.dist-info/WHEEL
python3_seco_range-1.0.2.dist-info/top_level.txt
python3_seco_range-1.0.2.dist-info/RECORD
