Metadata-Version: 2.1
Name: python3-seco-range
Version: 1.0.2
Summary: A Python 3 version of the library to interact with Range from ytoolshed
Home-page: https://github.com/xadrnd/range/tree/master/python_seco_range/source
Author: ytoolshed
License: UNKNOWN
Project-URL: Original Project, https://github.com/ytoolshed/range
Platform: UNKNOWN
Classifier: Programming Language :: Python :: 3
Classifier: Development Status :: 4 - Beta
Classifier: License :: OSI Approved :: BSD License
Classifier: Operating System :: OS Independent
Requires-Python: >=3.6
Requires-Dist: argparse
Requires-Dist: BeautifulSoup4
Requires-Dist: GitPython
Requires-Dist: PyYAML
Requires-Dist: requests
